askfm/__init__.py
askfm/answers.py
askfm/crawler.py
askfm/pair.py
askfm/parser.py
askfm.py-0.6.6.dist-info/LICENSE
askfm.py-0.6.6.dist-info/METADATA
askfm.py-0.6.6.dist-info/WHEEL
askfm.py-0.6.6.dist-info/top_level.txt
askfm.py-0.6.6.dist-info/RECORD
